melid/app.py
melid/layout.py
melid/processors.py
melid/router.py
melid/store.py
melid/types.py
melid/utils.py
melid/widgets.py
melid/tailwind/__init__.py
melid/tailwind/color.py
melid/tailwind/css_ast.py
melid/tailwind/size.py
melid/tailwind/utils.py
melid/tailwind/configs/color.py
melid/tailwind/configs/size.py
melid/tailwind/configs/variants.py
melid-1.0.17.dist-info/LICENSE
melid-1.0.17.dist-info/METADATA
melid-1.0.17.dist-info/WHEEL
melid-1.0.17.dist-info/top_level.txt
melid-1.0.17.dist-info/RECORD
