Metadata-Version: 2.1
Name: melid
Version: 1.0.17
Summary: Melid is a PyQt5 Library for Desktop Applications containing commonly used utils and advanced widget implementations in very simple forms.
Author-email: Mohammed Al-Ameen <ameenmohammed2311@gmail.com>
Project-URL: Homepage, https://github.com/struckchure/melid
Project-URL: Bug Tracker, https://github.com/struckchure/melid/issues
Classifier: Programming Language :: Python :: 3
Classifier: License :: OSI Approved :: MIT License
Classifier: Operating System :: OS Independent
Requires-Python: >=3.10
License-File: LICENSE
Requires-Dist: pyqt5 >=5.15.11
